uefi_firmware/__init__.py
uefi_firmware/base.py
uefi_firmware/efi_compressor.pypy37-pp73-win_amd64.pyd
uefi_firmware/flash.py
uefi_firmware/me.py
uefi_firmware/pfs.py
uefi_firmware/uefi.py
uefi_firmware/utils.py
uefi_firmware/generator/__init__.py
uefi_firmware/generator/uefi.py
uefi_firmware/guids/__init__.py
uefi_firmware/guids/efiguids.py
uefi_firmware/guids/efiguids_ami.py
uefi_firmware/guids/efiguids_asrock.py
uefi_firmware/guids/efiguids_dell.py
uefi_firmware/guids/efiguids_lenovo.py
uefi_firmware/guids/efiguids_qualcomm.py
uefi_firmware/misc/__init__.py
uefi_firmware/misc/checker.py
uefi_firmware/structs/__init__.py
uefi_firmware/structs/flash_structs.py
uefi_firmware/structs/intel_me_structs.py
uefi_firmware/structs/uefi_structs.py
uefi_firmware-1.11.data/headers/7zVersion.h
uefi_firmware-1.11.data/headers/BaseTypes.h
uefi_firmware-1.11.data/headers/Bra.h
uefi_firmware-1.11.data/headers/Compress.h
uefi_firmware-1.11.data/headers/CompressionTypes.h
uefi_firmware-1.11.data/headers/CpuArch.h
uefi_firmware-1.11.data/headers/Decompress.h
uefi_firmware-1.11.data/headers/EfiFile.h
uefi_firmware-1.11.data/headers/LzFind.h
uefi_firmware-1.11.data/headers/LzHash.h
uefi_firmware-1.11.data/headers/LzmaCompress.h
uefi_firmware-1.11.data/headers/LzmaDec.h
uefi_firmware-1.11.data/headers/LzmaDecompress.h
uefi_firmware-1.11.data/headers/LzmaEnc.h
uefi_firmware-1.11.data/headers/ProcessorBind.h
uefi_firmware-1.11.data/headers/Types.h
uefi_firmware-1.11.data/scripts/uefi-firmware-parser
uefi_firmware-1.11.dist-info/AUTHORS
uefi_firmware-1.11.dist-info/LICENSE
uefi_firmware-1.11.dist-info/METADATA
uefi_firmware-1.11.dist-info/WHEEL
uefi_firmware-1.11.dist-info/top_level.txt
uefi_firmware-1.11.dist-info/RECORD
