Metadata-Version: 2.1
Name: uefi_firmware
Version: 1.11
Summary: Various data structures and parsing tools for UEFI firmware.
Home-page: https://github.com/theopolis/uefi-firmware-parser
Author: Teddy Reed
Author-email: teddy@prosauce.org
License: BSD
Keywords: security uefi firmware parsing bios
Classifier: Development Status :: 4 - Beta
Classifier: Intended Audience :: System Administrators
Classifier: Topic :: Security
Classifier: License :: OSI Approved :: BSD License
Classifier: Programming Language :: Python :: 3
License-File: LICENSE
License-File: AUTHORS
